setup.py
lib/python_rest.egg-info/PKG-INFO
lib/python_rest.egg-info/SOURCES.txt
lib/python_rest.egg-info/dependency_links.txt
lib/python_rest.egg-info/entry_points.txt
lib/python_rest.egg-info/requires.txt
lib/python_rest.egg-info/top_level.txt
lib/rest/__init__.py
lib/rest/_version.py
lib/rest/api.py
lib/rest/application.py
lib/rest/collection.py
lib/rest/error.py
lib/rest/filter.py
lib/rest/http.py
lib/rest/mapper.py
lib/rest/msiis.py
lib/rest/protocol.py
lib/rest/proxy.py
lib/rest/request.py
lib/rest/resource.py
lib/rest/response.py
lib/rest/server.py
lib/rest/util.py
lib/rest/entity/__init__.py
lib/rest/entity/format.py
lib/rest/entity/hint.py
lib/rest/entity/json.py
lib/rest/entity/parse.py
lib/rest/entity/transform.py
lib/rest/entity/xml.py
lib/rest/entity/yaml.py
lib/rest/test/__init__.py
lib/rest/test/test_application.py
lib/rest/test/test_entity.py
lib/rest/test/test_http.py
lib/rest/test/test_mapper.py
lib/rest/test/test_proxy.py
lib/rest/test/test_request.py
lib/rest/test/test_response.py