Metadata-Version: 1.0
Name: python-rest
Version: 1.3
Summary: A mini-framework for creating RESTful applications.
Home-page: http://bitbucket.org/geertj/python-rest
Author: Geert Jansen
Author-email: geertj@gmail.com
License: MIT
Platform: UNKNOWN
Classifier: Development Status :: 4 - Beta
Classifier: Environment :: Web Environment
Classifier: Intended Audience :: Developers
Classifier: License :: OSI Approved :: MIT License
Classifier: Operating System :: OS Independent
Classifier: Programming Language :: Python
Classifier: Topic :: Internet :: WWW/HTTP :: WSGI :: Application
